MANIFEST.in
README.md
requirements.txt
setup.py
zutnlp/__init__.py
zutnlp/doc_utils.py
zutnlp.egg-info/PKG-INFO
zutnlp.egg-info/SOURCES.txt
zutnlp.egg-info/dependency_links.txt
zutnlp.egg-info/requires.txt
zutnlp.egg-info/top_level.txt
zutnlp/base/__init__.py
zutnlp/base/base_data.py
zutnlp/base/base_loss.py
zutnlp/base/base_model.py
zutnlp/base/base_trainer.py
zutnlp/common/__init__.py
zutnlp/common/data.py
zutnlp/common/models.py
zutnlp/common/trainer.py
zutnlp/utils/__init__.py
zutnlp/utils/test.py