Metadata-Version: 2.1
Name: zutnlp
Version: 0.0.1
Summary: zutnlp: Deep Learning Toolkit for NLP, developed by zutnlp Team
Home-page: https://gitee.com/natural_language_processing/zutnlp
Author: zutnlp Team
Author-email: 2020107239@zut.edu.cn
License: UNKNOWN
Platform: UNKNOWN
Requires-Python: >=3.6
